sportmonks/__init__.py
sportmonks/_base.py
sportmonks/_types.py
sportmonks/soccer.py
sportmonks_v2-2.0.1.dist-info/LICENSE
sportmonks_v2-2.0.1.dist-info/METADATA
sportmonks_v2-2.0.1.dist-info/WHEEL
sportmonks_v2-2.0.1.dist-info/top_level.txt
sportmonks_v2-2.0.1.dist-info/RECORD
