Metadata-Version: 2.1
Name: sportmonks-v2
Version: 2.0.1
Summary: Pythonic wrapper around SportMonks API.
Home-page: https://github.com/sebastiaanspeck/sportmonks
Author: Sebastiaan Speck
Author-email: shemspeck@gmail.com
License: MIT
Download-URL: https://pypi.org/project/sportmonks_v2/
Platform: UNKNOWN
Requires-Python: >=3.5.2
Requires-Dist: requests
